psycopg2_error/__init__.py
psycopg2_error/errors.py
psycopg2_error/handler.py
psycopg2_error_handler-0.0.4.dist-info/LICENSE
psycopg2_error_handler-0.0.4.dist-info/METADATA
psycopg2_error_handler-0.0.4.dist-info/WHEEL
psycopg2_error_handler-0.0.4.dist-info/top_level.txt
psycopg2_error_handler-0.0.4.dist-info/RECORD
