Metadata-Version: 2.1
Name: psycopg2-error-handler
Version: 0.0.4
Summary: Psycopg2 Error Handler
Home-page: UNKNOWN
Author: Alexander Lopatin
License: MIT
Platform: UNKNOWN
License-File: LICENSE
Requires-Dist: psycopg-binary (>=3.0)
